docs/conf.py
src/fixit/__init__.py
src/fixit/__main__.py
src/fixit/__version__.py
src/fixit/api.py
src/fixit/cli.py
src/fixit/config.py
src/fixit/engine.py
src/fixit/types.py
src/fixit/legacy/__init__.py
src/fixit/legacy/_version.py
src/fixit/legacy/rule_lint_engine.py
src/fixit/legacy/cli/__init__.py
src/fixit/legacy/cli/add_new_rule.py
src/fixit/legacy/cli/apply_fix.py
src/fixit/legacy/cli/args.py
src/fixit/legacy/cli/formatter.py
src/fixit/legacy/cli/full_repo_metadata.py
src/fixit/legacy/cli/init_config.py
src/fixit/legacy/cli/insert_suppressions.py
src/fixit/legacy/cli/main.py
src/fixit/legacy/cli/run_rules.py
src/fixit/legacy/cli/utils.py
src/fixit/legacy/common/__init__.py
src/fixit/legacy/common/autofix.py
src/fixit/legacy/common/base.py
src/fixit/legacy/common/comments.py
src/fixit/legacy/common/config.py
src/fixit/legacy/common/document.py
src/fixit/legacy/common/flake8_compat.py
src/fixit/legacy/common/full_repo_metadata.py
src/fixit/legacy/common/generate_pyre_fixtures.py
src/fixit/legacy/common/ignores.py
src/fixit/legacy/common/insert_suppressions.py
src/fixit/legacy/common/line_mapping.py
src/fixit/legacy/common/pseudo_rule.py
src/fixit/legacy/common/report.py
src/fixit/legacy/common/unused_suppressions.py
src/fixit/legacy/common/utils.py
src/fixit/legacy/common/cli/__init__.py
src/fixit/legacy/common/cli/args.py
src/fixit/legacy/common/cli/formatter.py
src/fixit/legacy/rules/__init__.py
src/fixit/legacy/rules/add_file_header.py
src/fixit/legacy/rules/avoid_or_in_except.py
src/fixit/legacy/rules/await_async_call.py
src/fixit/legacy/rules/chained_instance_check.py
src/fixit/legacy/rules/cls_in_classmethod.py
src/fixit/legacy/rules/compare_primitives_by_equal.py
src/fixit/legacy/rules/compare_singleton_primitives_by_is.py
src/fixit/legacy/rules/explicit_frozen_dataclass.py
src/fixit/legacy/rules/flake8_compat.py
src/fixit/legacy/rules/gather_sequential_await.py
src/fixit/legacy/rules/import_constraints.py
src/fixit/legacy/rules/no_assert_equals.py
fixit2-2.0.0a1.dist-info/METADATA
fixit2-2.0.0a1.dist-info/WHEEL
fixit2-2.0.0a1.dist-info/entry_points.txt
fixit2-2.0.0a1.dist-info/licenses/LICENSE
fixit2-2.0.0a1.dist-info/RECORD
