Metadata-Version: 2.1
Name: fixit2
Version: 2.0.0a1
Summary: A lint framework that writes better Python code for you.
Project-URL: Home, https://fixit.rtfd.io
Project-URL: Github, https://github.com/Instagram/Fixit
Project-URL: Changelog, https://github.com/Instagram/LibCST/blob/main/CHANGELOG.md
Author: Jimmy Lai, John Reese, Zsolt Dollenstein, Meta Platforms, Inc
License: MIT License
Classifier: Development Status :: 3 - Alpha
Classifier: Intended Audience :: Developers
Classifier: License :: OSI Approved :: MIT License
Classifier: Operating System :: OS Independent
Classifier: Programming Language :: Python
Classifier: Programming Language :: Python :: 3 :: Only
Classifier: Topic :: Software Development :: Libraries :: Python Modules
Classifier: Topic :: Software Development :: Quality Assurance
Requires-Python: >=3.7
Requires-Dist: click>=8.0
Requires-Dist: libcst>=0.3.18
Requires-Dist: tomli>=2.0; python_version < '3.11'
Requires-Dist: trailrunner>=1.2
